setup.py
roian/setup.py
roian_fwk.egg-info/PKG-INFO
roian_fwk.egg-info/SOURCES.txt
roian_fwk.egg-info/dependency_links.txt
roian_fwk.egg-info/requires.txt
roian_fwk.egg-info/top_level.txt