Metadata-Version: 1.0
Name: roian-fwk
Version: 0.1.1
Summary: simple tcf platform
Home-page: https://github.com/roian1974/platform
Author: roian
Author-email: changwskr@gmail.com
License: JWS
Platform: UNKNOWN
